{
  "title": "Diventa Socio",
  "intro": "Possono iscriversi i pugliesi nati in Puglia o aventi origine pugliese, coloro che pur nati in altre regioni e/o altri Paesi si sentono pugliesi, e quanti sentono di contribuire allo sviluppo economico, sociale, culturale ed imprenditoriale della Puglia.",
  "plans": [
    {
      "name": "Socio Ordinario",
      "description": "Per tutti i pugliesi e chi si sente tale. Con diritto di voto nelle assemblee dell'associazione.",
      "price": 20,
      "currency": "GBP",
      "features": [
        "Diritto di voto in assemblea",
        "Accesso a tutti gli eventi e festival",
        "Newsletter esclusiva",
        "Rete di contatti con altri pugliesi nel Regno Unito"
      ],
      "highlight": true,
      "stripeLink": ""
    },
    {
      "name": "Socio AWR",
      "label": "Apulia Worldwide Reference",
      "description": "Per aziende, imprese, liberi professionisti e attivita' presenti in Puglia, in altre regioni italiane o all'estero. Senza diritto di voto.",
      "price": 50,
      "currency": "GBP",
      "priceNote": "quota minima",
      "features": [
        "Pubblicita' gratuita della propria attivita' sul sito web",
        "Visibilita' nella rete Pugliesi nel Mondo",
        "Accesso a tutti gli eventi e festival",
        "Newsletter esclusiva",
        "Opportunita' di networking imprenditoriale"
      ],
      "highlight": false,
      "stripeLink": ""
    }
  ],
  "benefits": [
    "Partecipazione a eventi culturali, festival e iniziative dell'associazione",
    "Connessione con la comunita' pugliese nel Regno Unito e nel mondo",
    "Newsletter con aggiornamenti, opportunita' e novita'",
    "Supporto e orientamento per i pugliesi nel Regno Unito",
    "Contributo allo sviluppo economico, sociale e culturale della Puglia"
  ],
  "contact": {
    "email": "puglianelmondolondra@gmail.com",
    "phone": "07962 471804"
  }
}
